{
	"name": "relationship-sdpppuclba",
	"properties": {
		"Name": "relationship-sdpppuclba",
		"EntityType": "RELATIONSHIP",
		"Namespace": {
			"DatabaseName": "HealthcareProvidersv2"
		},
		"Origin": {
			"Type": "SPARK"
		},
		"FromTableName": "Warehouse",
		"ToTableName": "Order",
		"ColumnRelationshipInformations": [
			{
				"FromColumnName": "WarehouseId",
				"ToColumnName": "WarehouseId"
			}
		],
		"RelationshipType": 0,
		"Properties": {
			"DerivedModelRelationshipInfo": "{\"baseRelationship\":{\"fromEntity\":\"Warehouse.cdm.json/Warehouse\",\"toEntity\":\"Order.cdm.json/Order\",\"joinPairs\":[{\"fromAttribute\":\"WarehouseId\",\"toAttribute\":\"WarehouseId\"}]}}"
		}
	},
	"type": "RELATIONSHIP"
}