{
	"name": "relationship-amhgufamnp",
	"properties": {
		"Name": "relationship-amhgufamnp",
		"EntityType": "RELATIONSHIP",
		"Namespace": {
			"DatabaseName": "HealthcareProvidersv2"
		},
		"Origin": {
			"Type": "SPARK"
		},
		"FromTableName": "PatientName",
		"ToTableName": "PatientNameSuffix",
		"ColumnRelationshipInformations": [
			{
				"FromColumnName": "ServiceProviderId",
				"ToColumnName": "ServiceProviderId"
			}
		],
		"RelationshipType": 0,
		"Properties": {
			"DerivedModelRelationshipInfo": "{\"baseRelationship\":{\"fromEntity\":\"PatientName.cdm.json/PatientName\",\"toEntity\":\"PatientNameSuffix.cdm.json/PatientNameSuffix\",\"joinPairs\":[{\"fromAttribute\":\"ServiceProviderId\",\"toAttribute\":\"ServiceProviderId\"}]}}"
		}
	},
	"type": "RELATIONSHIP"
}